asyncz/__init__.py
asyncz/datastructures.py
asyncz/enums.py
asyncz/exceptions.py
asyncz/file_locking.py
asyncz/locks.py
asyncz/monkay.py
asyncz/protocols.py
asyncz/py.typed
asyncz/state.py
asyncz/typing.py
asyncz/utils.py
asyncz/cli/__init__.py
asyncz/cli/_parsers.py
asyncz/cli/app.py
asyncz/cli/bootstrap_loader.py
asyncz/cli/loader.py
asyncz/cli/types.py
asyncz/cli/utils.py
asyncz/cli/commands/__init__.py
asyncz/cli/commands/add.py
asyncz/cli/commands/list.py
asyncz/cli/commands/pause.py
asyncz/cli/commands/remove.py
asyncz/cli/commands/resume.py
asyncz/cli/commands/run.py
asyncz/cli/commands/start.py
asyncz/conf/__init__.py
asyncz/conf/global_settings.py
asyncz/contrib/__init__.py
asyncz/contrib/dashboard/__init__.py
asyncz/contrib/dashboard/application.py
asyncz/contrib/dashboard/config.py
asyncz/contrib/dashboard/engine.py
asyncz/contrib/dashboard/messages.py
asyncz/contrib/dashboard/mixins.py
asyncz/contrib/dashboard/admin/__init__.py
asyncz/contrib/dashboard/admin/backends.py
asyncz/contrib/dashboard/admin/core.py
asyncz/contrib/dashboard/admin/protocols.py
asyncz/contrib/dashboard/admin/middleware/__init__.py
asyncz/contrib/dashboard/admin/middleware/auth_gate.py
asyncz/contrib/dashboard/admin/middleware/forward_root_path.py
asyncz/contrib/dashboard/controllers/__init__.py
asyncz/contrib/dashboard/controllers/_helpers.py
asyncz/contrib/dashboard/controllers/home.py
asyncz/contrib/dashboard/controllers/logs.py
asyncz/contrib/dashboard/controllers/tasks.py
asyncz/contrib/dashboard/logs/__init__.py
asyncz/contrib/dashboard/logs/handler.py
asyncz/contrib/dashboard/logs/storage.py
asyncz/contrib/dashboard/statics/css/asyncz.css
asyncz/contrib/dashboard/statics/css/toastify.min.css
asyncz/contrib/dashboard/statics/js/asyncz.js
asyncz/contrib/dashboard/statics/js/toastify.min.js
asyncz/contrib/dashboard/templates/404.html
asyncz/contrib/dashboard/templates/index.html
asyncz/contrib/dashboard/templates/layout.html
asyncz/contrib/dashboard/templates/login.html
asyncz-0.14.3.dist-info/METADATA
asyncz-0.14.3.dist-info/WHEEL
asyncz-0.14.3.dist-info/entry_points.txt
asyncz-0.14.3.dist-info/licenses/LICENSE
asyncz-0.14.3.dist-info/RECORD
