Metadata-Version: 2.4
Name: asyncz
Version: 0.14.3
Summary: The scheduler that nobody wants but every application needs.
Project-URL: Homepage, https://github.com/dymmond/asyncz
Project-URL: Documentation, https://asyncz.dymmond.com/
Project-URL: Changelog, https://asyncz.dymmond.com/release-notes/
Project-URL: Funding, https://github.com/sponsors/tarsil
Project-URL: Source, https://github.com/dymmond/asyncz
Author-email: Tiago Silva <tiago.arasilva@gmail.com>
License-File: LICENSE
Keywords: apscheduler,asgi,asyncz,cron,fastapi,framework,pydantic,scheduler,starlette
Classifier: Development Status :: 5 - Production/Stable
Classifier: Environment :: Web Environment
Classifier: Framework :: AnyIO
Classifier: Framework :: AsyncIO
Classifier: Intended Audience :: Developers
Classifier: Intended Audience :: Information Technology
Classifier: Intended Audience :: System Administrators
Classifier: License :: OSI Approved :: BSD License
Classifier: Operating System :: OS Independent
Classifier: Programming Language :: Python
Classifier: Programming Language :: Python :: 3
Classifier: Programming Language :: Python :: 3 :: Only
Classifier: Programming Language :: Python :: 3.10
Classifier: Programming Language :: Python :: 3.11
Classifier: Programming Language :: Python :: 3.12
Classifier: Programming Language :: Python :: 3.13
Classifier: Programming Language :: Python :: 3.14
Classifier: Topic :: Internet
Classifier: Topic :: Internet :: WWW/HTTP
Classifier: Topic :: Internet :: WWW/HTTP :: HTTP Servers
Classifier: Topic :: Software Development
Classifier: Topic :: Software Development :: Libraries
Classifier: Topic :: Software Development :: Libraries :: Application Frameworks
Classifier: Topic :: Software Development :: Libraries :: Python Modules
Classifier: Typing :: Typed
Requires-Python: >=3.10
Requires-Dist: cryptography
Requires-Dist: monkay>=0.5.0
Requires-Dist: pydantic<3.0.0,>=2.5.3
Requires-Dist: sayer>=0.7.4
Provides-Extra: dashboard
Requires-Dist: lilya[standard]>=0.22.15; extra == 'dashboard'
Provides-Extra: docs
Requires-Dist: griffe-typingdoc<1.0,>=0.2.2; extra == 'docs'
Requires-Dist: mdx-include>=1.4.2; extra == 'docs'
Requires-Dist: mkdocs-macros-plugin>=0.4.0; extra == 'docs'
Requires-Dist: mkdocs-material>=9.4.4; extra == 'docs'
Requires-Dist: mkdocs-meta-descriptions-plugin>=2.3.0; extra == 'docs'
Requires-Dist: mkdocs<2.0.0,>=1.1.2; extra == 'docs'
Requires-Dist: mkdocstrings[python]>=0.23.0; extra == 'docs'
Requires-Dist: pyyaml<7.0.0,>=6.0; extra == 'docs'
Requires-Dist: sayer>=0.7.4; extra == 'docs'
Requires-Dist: typing-extensions>=3.10.0; extra == 'docs'
Provides-Extra: localtime
Requires-Dist: tzlocal; extra == 'localtime'
Provides-Extra: loguru
Requires-Dist: loguru<0.8.0,>=0.7.0; extra == 'loguru'
Provides-Extra: testing
Requires-Dist: freezegun; extra == 'testing'
Requires-Dist: httpx; extra == 'testing'
Requires-Dist: ipdb; extra == 'testing'
Requires-Dist: lilya[standard]>=0.22.15; extra == 'testing'
Requires-Dist: loguru<0.8.0,>=0.7.0; extra == 'testing'
Requires-Dist: mypy<2.0.0,>=0.982; extra == 'testing'
Requires-Dist: pymongo<5.0.0,>=4.3.3; extra == 'testing'
Requires-Dist: pytest-asyncio<2.0.0,>=1.0; extra == 'testing'
Requires-Dist: pytest-cov<8.0.0,>=2.12.0; extra == 'testing'
Requires-Dist: pytest-loguru<1,>=0.2.0; extra == 'testing'
Requires-Dist: pytest<10.0.0,>=7.1.3; extra == 'testing'
Requires-Dist: pytz>=2022.6; extra == 'testing'
Requires-Dist: ravyn>=0.1.0; extra == 'testing'
Requires-Dist: redis<8.0.0,>=4.4.0; extra == 'testing'
Requires-Dist: sqlalchemy; extra == 'testing'
Requires-Dist: starlette; extra == 'testing'
Requires-Dist: tzlocal; extra == 'testing'
